tts_webui_extension/seamless_m4t/__init__.py
tts_webui_extension/seamless_m4t/language_code_to_name.py
tts_webui_extension/seamless_m4t/main.py
tts_webui_extension_seamless_m4t-0.0.7.dist-info/licenses/LICENSE
tts_webui_extension_seamless_m4t-0.0.7.dist-info/METADATA
tts_webui_extension_seamless_m4t-0.0.7.dist-info/WHEEL
tts_webui_extension_seamless_m4t-0.0.7.dist-info/top_level.txt
tts_webui_extension_seamless_m4t-0.0.7.dist-info/RECORD
