Metadata-Version: 2.4
Name: tts_webui_extension.seamless_m4t
Version: 0.0.7
Summary: SeamlessM4T is a multilingual and multimodal translation model supporting text and speech
Home-page: https://github.com/rsxdalv/tts_webui_extension.seamless_m4t
Author: rsxdalv
Classifier: Programming Language :: Python :: 3
Classifier: License :: OSI Approved :: MIT License
Classifier: Operating System :: OS Independent
License-File: LICENSE
Requires-Dist: transformers>=4.30.0
Requires-Dist: torchaudio>=2.0.0
Dynamic: author
Dynamic: classifier
Dynamic: description
Dynamic: description-content-type
Dynamic: home-page
Dynamic: license-file
Dynamic: requires-dist
Dynamic: summary
